{"type":"root","label":null,"url":"","children":[{"type":"category","label":"LABIOS","url":"http:\/\/artmakeuproom.com\/index.php?id_category=85&controller=category","children":[{"type":"category","label":"Barras","url":"http:\/\/artmakeuproom.com\/index.php?id_category=88&controller=category","children":[],"open_in_new_window":false,"image_urls":[],"page_identifier":"category-88","current":false,"depth":2},{"type":"category","label":"Brillos","url":"http:\/\/artmakeuproom.com\/index.php?id_category=89&controller=category","children":[],"open_in_new_window":false,"image_urls":[],"page_identifier":"category-89","current":false,"depth":2},{"type":"category","label":"Perfiladores","url":"http:\/\/artmakeuproom.com\/index.php?id_category=90&controller=category","children":[],"open_in_new_window":false,"image_urls":[],"page_identifier":"category-90","current":false,"depth":2},{"type":"category","label":"Lip Care + Preparador","url":"http:\/\/artmakeuproom.com\/index.php?id_category=91&controller=category","children":[],"open_in_new_window":false,"image_urls":[],"page_identifier":"category-91","current":false,"depth":2},{"type":"category","label":"Paletas + Kits","url":"http:\/\/artmakeuproom.com\/index.php?id_category=92&controller=category","children":[],"open_in_new_window":false,"image_urls":[],"page_identifier":"category-92","current":false,"depth":2}],"open_in_new_window":false,"image_urls":[],"page_identifier":"category-85","current":false,"depth":1},{"type":"category","label":"OJOS","url":"http:\/\/artmakeuproom.com\/index.php?id_category=86&controller=category","children":[{"type":"category","label":"Sombras","url":"http:\/\/artmakeuproom.com\/index.php?id_category=93&controller=category","children":[],"open_in_new_window":false,"image_urls":[],"page_identifier":"category-93","current":false,"depth":2},{"type":"category","label":"Delineadores","url":"http:\/\/artmakeuproom.com\/index.php?id_category=94&controller=category","children":[],"open_in_new_window":false,"image_urls":[],"page_identifier":"category-94","current":false,"depth":2},{"type":"category","label":"M\u00e1scaras","url":"http:\/\/artmakeuproom.com\/index.php?id_category=95&controller=category","children":[],"open_in_new_window":false,"image_urls":[],"page_identifier":"category-95","current":false,"depth":2},{"type":"category","label":"Cejas","url":"http:\/\/artmakeuproom.com\/index.php?id_category=96&controller=category","children":[],"open_in_new_window":false,"image_urls":[],"page_identifier":"category-96","current":false,"depth":2},{"type":"category","label":"Pesta\u00f1as","url":"http:\/\/artmakeuproom.com\/index.php?id_category=97&controller=category","children":[],"open_in_new_window":false,"image_urls":[],"page_identifier":"category-97","current":false,"depth":2},{"type":"category","label":"Preparadores","url":"http:\/\/artmakeuproom.com\/index.php?id_category=98&controller=category","children":[],"open_in_new_window":false,"image_urls":[],"page_identifier":"category-98","current":false,"depth":2},{"type":"category","label":"Paletas + Kits","url":"http:\/\/artmakeuproom.com\/index.php?id_category=99&controller=category","children":[],"open_in_new_window":false,"image_urls":[],"page_identifier":"category-99","current":false,"depth":2}],"open_in_new_window":false,"image_urls":[],"page_identifier":"category-86","current":false,"depth":1},{"type":"category","label":"ROSTRO","url":"http:\/\/artmakeuproom.com\/index.php?id_category=87&controller=category","children":[{"type":"category","label":"Bases de Maquillaje","url":"http:\/\/artmakeuproom.com\/index.php?id_category=100&controller=category","children":[],"open_in_new_window":false,"image_urls":[],"page_identifier":"category-100","current":false,"depth":2},{"type":"category","label":"Polvos","url":"http:\/\/artmakeuproom.com\/index.php?id_category=101&controller=category","children":[],"open_in_new_window":false,"image_urls":[],"page_identifier":"category-101","current":false,"depth":2},{"type":"category","label":"Rubores","url":"http:\/\/artmakeuproom.com\/index.php?id_category=102&controller=category","children":[],"open_in_new_window":false,"image_urls":[],"page_identifier":"category-102","current":false,"depth":2},{"type":"category","label":"Correctores","url":"http:\/\/artmakeuproom.com\/index.php?id_category=103&controller=category","children":[],"open_in_new_window":false,"image_urls":[],"page_identifier":"category-103","current":false,"depth":2},{"type":"category","label":"Multiusos","url":"http:\/\/artmakeuproom.com\/index.php?id_category=104&controller=category","children":[],"open_in_new_window":false,"image_urls":[],"page_identifier":"category-104","current":false,"depth":2},{"type":"category","label":"Iluminadores + Contouring","url":"http:\/\/artmakeuproom.com\/index.php?id_category=105&controller=category","children":[],"open_in_new_window":false,"image_urls":[],"page_identifier":"category-105","current":false,"depth":2}],"open_in_new_window":false,"image_urls":[],"page_identifier":"category-87","current":false,"depth":1},{"type":"category","label":"PRODUCTOS PRO","url":"http:\/\/artmakeuproom.com\/index.php?id_category=106&controller=category","children":[],"open_in_new_window":false,"image_urls":[],"page_identifier":"category-106","current":false,"depth":1}],"open_in_new_window":false,"image_urls":[],"page_identifier":null,"depth":0}